InnerEye_DICOM_RT/__init__.py
InnerEye_DICOM_RT/nifti_to_dicom_rt_converter.py
InnerEye_DICOM_RT/bin/netcoreapp2.1/BitMiracle.LibJpeg.NetCore.dll
InnerEye_DICOM_RT/bin/netcoreapp2.1/CSJ2K.dll
InnerEye_DICOM_RT/bin/netcoreapp2.1/CommandLine.dll
InnerEye_DICOM_RT/bin/netcoreapp2.1/Dicom.Core.dll
InnerEye_DICOM_RT/bin/netcoreapp2.1/Echo.deps.json
InnerEye_DICOM_RT/bin/netcoreapp2.1/Echo.dll
InnerEye_DICOM_RT/bin/netcoreapp2.1/Echo.pdb
InnerEye_DICOM_RT/bin/netcoreapp2.1/Echo.runtimeconfig.json
InnerEye_DICOM_RT/bin/netcoreapp2.1/LZ4.dll
InnerEye_DICOM_RT/bin/netcoreapp2.1/LZ4pn.dll
InnerEye_DICOM_RT/bin/netcoreapp2.1/Microsoft.RTConvert.Common.dll
InnerEye_DICOM_RT/bin/netcoreapp2.1/Microsoft.RTConvert.Common.pdb
InnerEye_DICOM_RT/bin/netcoreapp2.1/Microsoft.RTConvert.Console.deps.json
InnerEye_DICOM_RT/bin/netcoreapp2.1/Microsoft.RTConvert.Console.dll
InnerEye_DICOM_RT/bin/netcoreapp2.1/Microsoft.RTConvert.Console.pdb
InnerEye_DICOM_RT/bin/netcoreapp2.1/Microsoft.RTConvert.Console.runtimeconfig.json
InnerEye_DICOM_RT/bin/netcoreapp2.1/Microsoft.RTConvert.Contours.dll
InnerEye_DICOM_RT/bin/netcoreapp2.1/Microsoft.RTConvert.Contours.pdb
InnerEye_DICOM_RT/bin/netcoreapp2.1/Microsoft.RTConvert.Converters.dll
InnerEye_DICOM_RT/bin/netcoreapp2.1/Microsoft.RTConvert.Converters.pdb
InnerEye_DICOM_RT/bin/netcoreapp2.1/Microsoft.RTConvert.MedIO.dll
InnerEye_DICOM_RT/bin/netcoreapp2.1/Microsoft.RTConvert.MedIO.pdb
InnerEye_DICOM_RT/bin/netcoreapp2.1/Microsoft.RTConvert.Models.dll
InnerEye_DICOM_RT/bin/netcoreapp2.1/Microsoft.RTConvert.Models.pdb
InnerEye_DICOM_RT/bin/netcoreapp2.1/csharls.dll
InnerEye_DICOM_RT/bin/netcoreapp2.1/runtimes/unix/lib/netstandard1.3/System.Data.SqlClient.dll
InnerEye_DICOM_RT/bin/netcoreapp2.1/runtimes/unix/lib/netstandard1.3/System.Text.Encoding.CodePages.dll
InnerEye_DICOM_RT/bin/netcoreapp2.1/runtimes/win/lib/netstandard1.3/System.Data.SqlClient.dll
InnerEye_DICOM_RT-1.1.0.dist-info/LICENSE
InnerEye_DICOM_RT-1.1.0.dist-info/METADATA
InnerEye_DICOM_RT-1.1.0.dist-info/WHEEL
InnerEye_DICOM_RT-1.1.0.dist-info/top_level.txt
InnerEye_DICOM_RT-1.1.0.dist-info/RECORD
