Metadata-Version: 2.1
Name: InnerEye-DICOM-RT
Version: 1.1.0
Summary: InnerEye DICOM to Nifti conversion functions
Home-page: https://github.com/microsoft/InnerEye-DICOM-RT
Author: Microsoft Research Cambridge InnerEye Team 
Author-email: innereyedev@microsoft.com
License: MIT License
Keywords: InnerEye,DICOM-RT,Nifti
Platform: UNKNOWN
Classifier: Development Status :: 3 - Alpha
Classifier: Intended Audience :: Science/Research
Classifier: Topic :: Scientific/Engineering :: Medical Science Apps.
Classifier: License :: OSI Approved :: MIT License
Classifier: Programming Language :: Python :: 3.7
Requires-Dist: dotnetcore2 (==2.1.23)
